tests/__init__.py
tests/test_api_transactions.py
tests/test_publisher_reader.py
tests/test_publisher_writer.py
tests/test_whale_alert.py
whale_alert-0.0.4.data/scripts/whaleAlertLogger
whalealert/__init__.py
whalealert/_version.py
whalealert/settings.py
whalealert/whalealert.py
whalealert/api/__init__.py
whalealert/api/transactions.py
whalealert/publisher/__init__.py
whalealert/publisher/reader.py
whalealert/publisher/writer.py
whale_alert-0.0.4.dist-info/LICENSE
whale_alert-0.0.4.dist-info/METADATA
whale_alert-0.0.4.dist-info/WHEEL
whale_alert-0.0.4.dist-info/top_level.txt
whale_alert-0.0.4.dist-info/RECORD
