Metadata-Version: 2.1
Name: whale-alert
Version: 0.0.4
Summary: Cryptocurrency Whale Alert API Logger
Home-page: https://github.com/stuianna/whaleAlert
Author: stuianna
Author-email: stuian@protonmail.com
License: UNKNOWN
Platform: UNKNOWN
Classifier: Programming Language :: Python :: 3
Classifier: License :: OSI Approved :: MIT License
Classifier: Operating System :: OS Independent
Requires-Python: >=3.6
Requires-Dist: requests
Requires-Dist: colorama
Requires-Dist: config-checker
Requires-Dist: db-ops
Requires-Dist: pandas
Requires-Dist: numpy
Requires-Dist: appdirs
Requires-Dist: python-dateutil
Requires-Dist: urllib3
